automaton/__init__.py
automaton/actions/__init__.py
automaton/actions/action.py
automaton/actions/action_emitter.py
automaton/actions/context.py
automaton/actions/hotkey.py
automaton/actions/hotstring.py
automaton/actions/macro.py
automaton/actions/redirect.py
automaton/actions/remap.py
automaton/core/__init__.py
automaton/core/actionstring.py
automaton/core/consts.py
automaton/core/device.py
automaton/core/input.py
automaton/core/inputstream.py
automaton/core/peripheral.py
automaton_linux-1.2.2.dist-info/LICENSE.txt
automaton_linux-1.2.2.dist-info/WHEEL
automaton_linux-1.2.2.dist-info/METADATA
automaton_linux-1.2.2.dist-info/RECORD
